dammy7878_pixegami_hello/__init__.py
dammy7878_pixegami_hello/main.py
dammy7878_pixegami_hello-0.5.0.dist-info/METADATA
dammy7878_pixegami_hello-0.5.0.dist-info/WHEEL
dammy7878_pixegami_hello-0.5.0.dist-info/entry_points.txt
dammy7878_pixegami_hello-0.5.0.dist-info/top_level.txt
dammy7878_pixegami_hello-0.5.0.dist-info/RECORD
