Metadata-Version: 2.1
Name: dammy7878-pixegami-hello
Version: 0.5.0
